marimo_flow/__init__.py
marimo_flow/core/__init__.py
marimo_flow/core/callbacks.py
marimo_flow/core/model_factory.py
marimo_flow/core/modeling.py
marimo_flow/core/problem.py
marimo_flow/core/problem_manager.py
marimo_flow/core/solver_manager.py
marimo_flow/core/training.py
marimo_flow/core/visualization.py
marimo_flow/core/walrus.py
marimo_flow/snippets/__init__.py
marimo_flow/snippets/charts.py
marimo_flow/snippets/dataframes.py
marimo_flow-0.2.0.dist-info/licenses/LICENSE
marimo_flow-0.2.0.dist-info/METADATA
marimo_flow-0.2.0.dist-info/WHEEL
marimo_flow-0.2.0.dist-info/top_level.txt
marimo_flow-0.2.0.dist-info/RECORD
