Metadata-Version: 2.4
Name: marimo-flow
Version: 0.2.0
Summary: Marimo Flow - Interactive ML notebooks with MLflow integration
Author-email: Bjoern Bethge <bjoern.bethge@gmail.com>
License-Expression: MIT
Project-URL: Homepage, https://github.com/bjoernbethge/marimo-flow
Project-URL: Repository, https://github.com/bjoernbethge/marimo-flow
Keywords: marimo,mlflow,machine-learning,notebooks,interactive
Classifier: Development Status :: 3 - Alpha
Classifier: Intended Audience :: Developers
Classifier: Intended Audience :: Science/Research
Classifier: Operating System :: OS Independent
Classifier: Programming Language :: Python :: 3
Classifier: Programming Language :: Python :: 3.11
Classifier: Programming Language :: Python :: 3.12
Classifier: Programming Language :: Python :: 3.13
Classifier: Topic :: Scientific/Engineering :: Artificial Intelligence
Classifier: Topic :: Software Development :: Libraries :: Python Modules
Requires-Python: >=3.11
License-File: LICENSE
Requires-Dist: marimo[lsp,mcp,recommended,sql]>=0.18.0
Requires-Dist: mlflow[genai,mcp]>=2.19.0
Requires-Dist: pina-mathlab>=0.2.1
Requires-Dist: transformers[accelerate,sentencepiece,tiktoken]>=4.55.0
Provides-Extra: ml
Requires-Dist: altair>=5.5.0; extra == "ml"
Requires-Dist: numpy>=2.1.2; extra == "ml"
Requires-Dist: optuna>=3.0.0; extra == "ml"
Requires-Dist: polars>=1.17.0; extra == "ml"
Requires-Dist: scikit-learn>=1.5.2; extra == "ml"
Requires-Dist: vegafusion>=1.7.4; extra == "ml"
Provides-Extra: llm
Requires-Dist: langchain>=0.3.0; extra == "llm"
Requires-Dist: langchain-community>=0.3.0; extra == "llm"
Requires-Dist: langchain-openai>=0.2.0; extra == "llm"
Requires-Dist: sentence-transformers>=5.1.0; extra == "llm"
Provides-Extra: openvino
Requires-Dist: httpx>=0.28.1; extra == "openvino"
Requires-Dist: openvino>=2025.3.0; extra == "openvino"
Provides-Extra: apps
Requires-Dist: astrophot>=0.16.1; extra == "apps"
Requires-Dist: astropy>=6.1.2; extra == "apps"
Requires-Dist: duckdb>=1.1.4; extra == "apps"
Requires-Dist: nbformat>=5.10.4; extra == "apps"
Requires-Dist: plotly>=5.24.0; extra == "apps"
Provides-Extra: full
Requires-Dist: marimo-flow[apps,llm,ml,openvino]; extra == "full"
Requires-Dist: torch>=2.5.1; extra == "full"
Requires-Dist: torch-geometric>=2.6.0; extra == "full"
Dynamic: license-file
